pytracing/__init__.py
pytracing/pytracing.py
pytracing-0.4.dist-info/DESCRIPTION.rst
pytracing-0.4.dist-info/METADATA
pytracing-0.4.dist-info/RECORD
pytracing-0.4.dist-info/WHEEL
pytracing-0.4.dist-info/metadata.json
pytracing-0.4.dist-info/top_level.txt
