Metadata-Version: 2.0
Name: pytracing
Version: 0.4
Summary: a python trace profiler that outputs to chrome trace-viewer format (about://tracing).
Home-page: https://www.github.com/kwlzn/pytracing
Author: Kris Wilson
Author-email: kwilson@twitter.com
License: UNKNOWN
Platform: UNKNOWN
